nonebot_plugin_learning_chat/__init__.py
nonebot_plugin_learning_chat/config.py
nonebot_plugin_learning_chat/handler.py
nonebot_plugin_learning_chat/models.py
nonebot_plugin_learning_chat/web_api.py
nonebot_plugin_learning_chat/web_page.py
nonebot_plugin_learning_chat-0.4.0.dist-info/LICENSE
nonebot_plugin_learning_chat-0.4.0.dist-info/METADATA
nonebot_plugin_learning_chat-0.4.0.dist-info/WHEEL
nonebot_plugin_learning_chat-0.4.0.dist-info/RECORD
