Metadata-Version: 2.1
Name: nonebot_plugin_learning_chat
Version: 0.4.0
Summary: Nonebot2 plugin to learn what your group members say.
Home-page: https://github.com/CMHopeSunshine/nonebot-plugin-learning-chat
License: AGPL
Keywords: nonebot2
Author: CMHopeSunshine
Author-email: 277073121@qq.com
Requires-Python: >=3.8,<4.0
Classifier: License :: Other/Proprietary License
Classifier: Programming Language :: Python :: 3
Classifier: Programming Language :: Python :: 3.8
Classifier: Programming Language :: Python :: 3.9
Classifier: Programming Language :: Python :: 3.10
Classifier: Programming Language :: Python :: 3.11
Requires-Dist: amis-python (>=1.0.6,<2.0.0)
Requires-Dist: jieba (>=0.42.1,<0.43.0)
Requires-Dist: nonebot-adapter-onebot (>=2.1,<3.0)
Requires-Dist: nonebot-plugin-apscheduler (>=0.2.0,<0.3.0)
Requires-Dist: nonebot-plugin-tortoise-orm (>=0.1.1)
Requires-Dist: nonebot2[fastapi] (>=2.0.0,<3.0.0)
Requires-Dist: python-jose (>=3.3.0,<4.0.0)
Requires-Dist: ruamel.yaml (>=0.17.21,<0.18.0)
Requires-Dist: tortoise-orm (>=0.20.0)
